{
  "updated": "2026-06-09T15:52:01.122Z",
  "summary": {
    "critical": 0,
    "high": 0,
    "medium": 0,
    "low": 34
  },
  "stocks": [
    {
      "n": "信维通信",
      "c": "300136",
      "m": 0,
      "eco": "马斯克",
      "tier": "T2星链",
      "risk": {
        "score": 0,
        "level": "低",
        "color": "#22c55e",
        "alerts": []
      },
      "lockups": [],
      "pledge": {
        "topPledgeRatio": 0,
        "topHolder": "",
        "totalPledge": 0
      },
      "goodwill": {
        "goodwill": 0,
        "netAssets": 1,
        "ratio": 0,
        "reportDate": "2026-03-31 00:00:00"
      },
      "changes": [],
      "checkedAt": "2026-06-09T15:51:37.150Z"
    },
    {
      "n": "阳光电源",
      "c": "300274",
      "m": 0,
      "eco": "",
      "tier": "",
      "risk": {
        "score": 0,
        "level": "低",
        "color": "#22c55e",
        "alerts": []
      },
      "lockups": [],
      "pledge": {
        "topPledgeRatio": 0,
        "topHolder": "",
        "totalPledge": 0
      },
      "goodwill": {
        "goodwill": 0,
        "netAssets": 1,
        "ratio": 0,
        "reportDate": "2026-03-31 00:00:00"
      },
      "changes": [],
      "checkedAt": "2026-06-09T15:52:00.562Z"
    },
    {
      "n": "中际旭创",
      "c": "300308",
      "m": 0,
      "eco": "英伟达",
      "tier": "T1.5光模块",
      "risk": {
        "score": 0,
        "level": "低",
        "color": "#22c55e",
        "alerts": []
      },
      "lockups": [],
      "pledge": {
        "topPledgeRatio": 0,
        "topHolder": "",
        "totalPledge": 0
      },
      "goodwill": {
        "goodwill": 0,
        "netAssets": 1,
        "ratio": 0,
        "reportDate": "2026-03-31 00:00:00"
      },
      "changes": [],
      "checkedAt": "2026-06-09T15:51:42.398Z"
    },
    {
      "n": "天孚通信",
      "c": "300394",
      "m": 0,
      "eco": "英伟达",
      "tier": "T1.5 CPO",
      "risk": {
        "score": 0,
        "level": "低",
        "color": "#22c55e",
        "alerts": []
      },
      "lockups": [],
      "pledge": {
        "topPledgeRatio": 0,
        "topHolder": "",
        "totalPledge": 0
      },
      "goodwill": {
        "goodwill": 0,
        "netAssets": 1,
        "ratio": 0,
        "reportDate": "2026-03-31 00:00:00"
      },
      "changes": [],
      "checkedAt": "2026-06-09T15:51:43.244Z"
    },
    {
      "n": "菲利华",
      "c": "300395",
      "m": 0,
      "eco": "",
      "tier": "",
      "risk": {
        "score": 0,
        "level": "低",
        "color": "#22c55e",
        "alerts": []
      },
      "lockups": [],
      "pledge": {
        "topPledgeRatio": 0,
        "topHolder": "",
        "totalPledge": 0
      },
      "goodwill": {
        "goodwill": 0,
        "netAssets": 1,
        "ratio": 0,
        "reportDate": "2026-03-31 00:00:00"
      },
      "changes": [],
      "checkedAt": "2026-06-09T15:51:55.622Z"
    },
    {
      "n": "蓝思科技",
      "c": "300433",
      "m": 0,
      "eco": "",
      "tier": "",
      "risk": {
        "score": 0,
        "level": "低",
        "color": "#22c55e",
        "alerts": []
      },
      "lockups": [],
      "pledge": {
        "topPledgeRatio": 0,
        "topHolder": "",
        "totalPledge": 0
      },
      "goodwill": {
        "goodwill": 0,
        "netAssets": 1,
        "ratio": 0,
        "reportDate": "2026-03-31 00:00:00"
      },
      "changes": [],
      "checkedAt": "2026-06-09T15:51:48.810Z"
    },
    {
      "n": "胜宏科技",
      "c": "300476",
      "m": 0,
      "eco": "英伟达",
      "tier": "T2 PCB",
      "risk": {
        "score": 0,
        "level": "低",
        "color": "#22c55e",
        "alerts": []
      },
      "lockups": [],
      "pledge": {
        "topPledgeRatio": 0,
        "topHolder": "",
        "totalPledge": 0
      },
      "goodwill": {
        "goodwill": 0,
        "netAssets": 1,
        "ratio": 0,
        "reportDate": "2026-03-31 00:00:00"
      },
      "changes": [],
      "checkedAt": "2026-06-09T15:51:41.296Z"
    },
    {
      "n": "新易盛",
      "c": "300502",
      "m": 0,
      "eco": "英伟达",
      "tier": "T1.5 CPO",
      "risk": {
        "score": 0,
        "level": "低",
        "color": "#22c55e",
        "alerts": []
      },
      "lockups": [],
      "pledge": {
        "topPledgeRatio": 0,
        "topHolder": "",
        "totalPledge": 0
      },
      "goodwill": {
        "goodwill": 0,
        "netAssets": 1,
        "ratio": 0,
        "reportDate": "2026-03-31 00:00:00"
      },
      "changes": [],
      "checkedAt": "2026-06-09T15:51:45.788Z"
    },
    {
      "n": "宁德时代",
      "c": "300750",
      "m": 0,
      "eco": "",
      "tier": "",
      "risk": {
        "score": 0,
        "level": "低",
        "color": "#22c55e",
        "alerts": []
      },
      "lockups": [],
      "pledge": {
        "topPledgeRatio": 0,
        "topHolder": "",
        "totalPledge": 0
      },
      "goodwill": {
        "goodwill": 0,
        "netAssets": 1,
        "ratio": 0,
        "reportDate": "2026-03-31 00:00:00"
      },
      "changes": [],
      "checkedAt": "2026-06-09T15:51:52.933Z"
    },
    {
      "n": "图南股份",
      "c": "300855",
      "m": 0,
      "eco": "",
      "tier": "",
      "risk": {
        "score": 0,
        "level": "低",
        "color": "#22c55e",
        "alerts": []
      },
      "lockups": [],
      "pledge": {
        "topPledgeRatio": 0,
        "topHolder": "",
        "totalPledge": 0
      },
      "goodwill": {
        "goodwill": 0,
        "netAssets": 1,
        "ratio": 0,
        "reportDate": "2026-03-31 00:00:00"
      },
      "changes": [],
      "checkedAt": "2026-06-09T15:51:56.439Z"
    },
    {
      "n": "超捷股份",
      "c": "301005",
      "m": 0,
      "eco": "",
      "tier": "",
      "risk": {
        "score": 0,
        "level": "低",
        "color": "#22c55e",
        "alerts": []
      },
      "lockups": [],
      "pledge": {
        "topPledgeRatio": 0,
        "topHolder": "",
        "totalPledge": 0
      },
      "goodwill": {
        "goodwill": 0,
        "netAssets": 1,
        "ratio": 0,
        "reportDate": "2026-03-31 00:00:00"
      },
      "changes": [],
      "checkedAt": "2026-06-09T15:51:50.738Z"
    },
    {
      "n": "生益科技",
      "c": "600183",
      "m": 1,
      "eco": "英伟达",
      "tier": "T3 CCL",
      "risk": {
        "score": 0,
        "level": "低",
        "color": "#22c55e",
        "alerts": []
      },
      "lockups": [],
      "pledge": {
        "topPledgeRatio": 0,
        "topHolder": "",
        "totalPledge": 0
      },
      "goodwill": {
        "goodwill": 0,
        "netAssets": 1,
        "ratio": 0,
        "reportDate": "2026-03-31 00:00:00"
      },
      "changes": [],
      "checkedAt": "2026-06-09T15:51:45.160Z"
    },
    {
      "n": "长电科技",
      "c": "600584",
      "m": 1,
      "eco": "英伟达",
      "tier": "T2封测",
      "risk": {
        "score": 0,
        "level": "低",
        "color": "#22c55e",
        "alerts": []
      },
      "lockups": [],
      "pledge": {
        "topPledgeRatio": 0,
        "topHolder": "",
        "totalPledge": 0
      },
      "goodwill": {
        "goodwill": 0,
        "netAssets": 1,
        "ratio": 0,
        "reportDate": "2026-03-31 00:00:00"
      },
      "changes": [],
      "checkedAt": "2026-06-09T15:51:48.196Z"
    },
    {
      "n": "工业富联",
      "c": "601138",
      "m": 1,
      "eco": "英伟达",
      "tier": "T1.5服务器",
      "risk": {
        "score": 0,
        "level": "低",
        "color": "#22c55e",
        "alerts": []
      },
      "lockups": [],
      "pledge": {
        "topPledgeRatio": 0,
        "topHolder": "",
        "totalPledge": 0
      },
      "goodwill": {
        "goodwill": 0,
        "netAssets": 1,
        "ratio": 0,
        "reportDate": "2026-03-31 00:00:00"
      },
      "changes": [],
      "checkedAt": "2026-06-09T15:51:41.924Z"
    },
    {
      "n": "拓普集团",
      "c": "601689",
      "m": 1,
      "eco": "马斯克",
      "tier": "T2特斯拉",
      "risk": {
        "score": 0,
        "level": "低",
        "color": "#22c55e",
        "alerts": []
      },
      "lockups": [],
      "pledge": {
        "topPledgeRatio": 0,
        "topHolder": "",
        "totalPledge": 0
      },
      "goodwill": {
        "goodwill": 0,
        "netAssets": 1,
        "ratio": 0,
        "reportDate": "2026-03-31 00:00:00"
      },
      "changes": [],
      "checkedAt": "2026-06-09T15:51:38.358Z"
    },
    {
      "n": "旭升集团",
      "c": "603305",
      "m": 1,
      "eco": "马斯克",
      "tier": "T3特斯拉",
      "risk": {
        "score": 0,
        "level": "低",
        "color": "#22c55e",
        "alerts": []
      },
      "lockups": [],
      "pledge": {
        "topPledgeRatio": 0,
        "topHolder": "",
        "totalPledge": 0
      },
      "goodwill": {
        "goodwill": 0,
        "netAssets": 0,
        "ratio": 0,
        "reportDate": ""
      },
      "changes": [],
      "checkedAt": "2026-06-09T15:51:39.463Z"
    },
    {
      "n": "豪能股份",
      "c": "603809",
      "m": 1,
      "eco": "",
      "tier": "",
      "risk": {
        "score": 0,
        "level": "低",
        "color": "#22c55e",
        "alerts": []
      },
      "lockups": [],
      "pledge": {
        "topPledgeRatio": 0,
        "topHolder": "",
        "totalPledge": 0
      },
      "goodwill": {
        "goodwill": 0,
        "netAssets": 1,
        "ratio": 0,
        "reportDate": "2026-03-31 00:00:00"
      },
      "changes": [],
      "checkedAt": "2026-06-09T15:51:49.999Z"
    },
    {
      "n": "兆易创新",
      "c": "603986",
      "m": 1,
      "eco": "",
      "tier": "",
      "risk": {
        "score": 0,
        "level": "低",
        "color": "#22c55e",
        "alerts": []
      },
      "lockups": [],
      "pledge": {
        "topPledgeRatio": 0,
        "topHolder": "",
        "totalPledge": 0
      },
      "goodwill": {
        "goodwill": 0,
        "netAssets": 1,
        "ratio": 0,
        "reportDate": "2026-03-31 00:00:00"
      },
      "changes": [],
      "checkedAt": "2026-06-09T15:52:01.121Z"
    },
    {
      "n": "绿的谐波",
      "c": "688017",
      "m": 1,
      "eco": "马斯克",
      "tier": "T3 Optimus",
      "risk": {
        "score": 0,
        "level": "低",
        "color": "#22c55e",
        "alerts": []
      },
      "lockups": [],
      "pledge": {
        "topPledgeRatio": 0,
        "topHolder": "",
        "totalPledge": 0
      },
      "goodwill": {
        "goodwill": 0,
        "netAssets": 1,
        "ratio": 0,
        "reportDate": "2026-03-31 00:00:00"
      },
      "changes": [],
      "checkedAt": "2026-06-09T15:51:40.682Z"
    },
    {
      "n": "斯瑞新材",
      "c": "688102",
      "m": 1,
      "eco": "",
      "tier": "",
      "risk": {
        "score": 0,
        "level": "低",
        "color": "#22c55e",
        "alerts": []
      },
      "lockups": [],
      "pledge": {
        "topPledgeRatio": 0,
        "topHolder": "",
        "totalPledge": 0
      },
      "goodwill": {
        "goodwill": 0,
        "netAssets": 1,
        "ratio": 0,
        "reportDate": "2026-03-31 00:00:00"
      },
      "changes": [],
      "checkedAt": "2026-06-09T15:51:49.438Z"
    },
    {
      "n": "寒武纪",
      "c": "688256",
      "m": 1,
      "eco": "",
      "tier": "",
      "risk": {
        "score": 0,
        "level": "低",
        "color": "#22c55e",
        "alerts": []
      },
      "lockups": [],
      "pledge": {
        "topPledgeRatio": 0,
        "topHolder": "",
        "totalPledge": 0
      },
      "goodwill": {
        "goodwill": 0,
        "netAssets": 1,
        "ratio": 0,
        "reportDate": "2026-03-31 00:00:00"
      },
      "changes": [],
      "checkedAt": "2026-06-09T15:51:51.783Z"
    },
    {
      "n": "天合光能",
      "c": "688599",
      "m": 1,
      "eco": "",
      "tier": "",
      "risk": {
        "score": 0,
        "level": "低",
        "color": "#22c55e",
        "alerts": []
      },
      "lockups": [],
      "pledge": {
        "topPledgeRatio": 0,
        "topHolder": "",
        "totalPledge": 0
      },
      "goodwill": {
        "goodwill": 0,
        "netAssets": 1,
        "ratio": 0,
        "reportDate": "2026-03-31 00:00:00"
      },
      "changes": [],
      "checkedAt": "2026-06-09T15:51:59.910Z"
    },
    {
      "n": "中芯国际",
      "c": "688981",
      "m": 1,
      "eco": "",
      "tier": "",
      "risk": {
        "score": 0,
        "level": "低",
        "color": "#22c55e",
        "alerts": []
      },
      "lockups": [],
      "pledge": {
        "topPledgeRatio": 0,
        "topHolder": "",
        "totalPledge": 0
      },
      "goodwill": {
        "goodwill": 0,
        "netAssets": 1,
        "ratio": 0,
        "reportDate": "2026-03-31 00:00:00"
      },
      "changes": [],
      "checkedAt": "2026-06-09T15:51:59.114Z"
    },
    {
      "n": "西部材料",
      "c": "002149",
      "m": 0,
      "eco": "马斯克",
      "tier": "T3火箭",
      "risk": {
        "score": 0,
        "level": "低",
        "color": "#22c55e",
        "alerts": []
      },
      "lockups": [],
      "pledge": {
        "topPledgeRatio": 0,
        "topHolder": "",
        "totalPledge": 0
      },
      "goodwill": {
        "goodwill": 0,
        "netAssets": 1,
        "ratio": 0,
        "reportDate": "2026-03-31 00:00:00"
      },
      "changes": [],
      "checkedAt": "2026-06-09T15:51:37.733Z"
    },
    {
      "n": "三花智控",
      "c": "002050",
      "m": 0,
      "eco": "马斯克",
      "tier": "T2特斯拉",
      "risk": {
        "score": 0,
        "level": "低",
        "color": "#22c55e",
        "alerts": []
      },
      "lockups": [],
      "pledge": {
        "topPledgeRatio": 0,
        "topHolder": "",
        "totalPledge": 0
      },
      "goodwill": {
        "goodwill": 0,
        "netAssets": 1,
        "ratio": 0,
        "reportDate": "2026-03-31 00:00:00"
      },
      "changes": [],
      "checkedAt": "2026-06-09T15:51:38.940Z"
    },
    {
      "n": "沪电股份",
      "c": "002463",
      "m": 0,
      "eco": "英伟达",
      "tier": "T2 PCB",
      "risk": {
        "score": 0,
        "level": "低",
        "color": "#22c55e",
        "alerts": []
      },
      "lockups": [],
      "pledge": {
        "topPledgeRatio": 0,
        "topHolder": "",
        "totalPledge": 0
      },
      "goodwill": {
        "goodwill": 0,
        "netAssets": 1,
        "ratio": 0,
        "reportDate": "2026-03-31 00:00:00"
      },
      "changes": [],
      "checkedAt": "2026-06-09T15:51:44.368Z"
    },
    {
      "n": "英维克",
      "c": "002837",
      "m": 0,
      "eco": "英伟达",
      "tier": "T1.5液冷",
      "risk": {
        "score": 0,
        "level": "低",
        "color": "#22c55e",
        "alerts": []
      },
      "lockups": [],
      "pledge": {
        "topPledgeRatio": 0,
        "topHolder": "",
        "totalPledge": 0
      },
      "goodwill": {
        "goodwill": 0,
        "netAssets": 1,
        "ratio": 0,
        "reportDate": "2026-03-31 00:00:00"
      },
      "changes": [],
      "checkedAt": "2026-06-09T15:51:46.655Z"
    },
    {
      "n": "麦格米特",
      "c": "002851",
      "m": 0,
      "eco": "英伟达",
      "tier": "T1.5电源",
      "risk": {
        "score": 0,
        "level": "低",
        "color": "#22c55e",
        "alerts": []
      },
      "lockups": [],
      "pledge": {
        "topPledgeRatio": 0,
        "topHolder": "",
        "totalPledge": 0
      },
      "goodwill": {
        "goodwill": 0,
        "netAssets": 1,
        "ratio": 0,
        "reportDate": "2026-03-31 00:00:00"
      },
      "changes": [],
      "checkedAt": "2026-06-09T15:51:47.141Z"
    },
    {
      "n": "科大讯飞",
      "c": "002230",
      "m": 0,
      "eco": "",
      "tier": "",
      "risk": {
        "score": 0,
        "level": "低",
        "color": "#22c55e",
        "alerts": []
      },
      "lockups": [],
      "pledge": {
        "topPledgeRatio": 0,
        "topHolder": "",
        "totalPledge": 0
      },
      "goodwill": {
        "goodwill": 0,
        "netAssets": 1,
        "ratio": 0,
        "reportDate": "2026-03-31 00:00:00"
      },
      "changes": [],
      "checkedAt": "2026-06-09T15:51:52.426Z"
    },
    {
      "n": "北方华创",
      "c": "002371",
      "m": 0,
      "eco": "",
      "tier": "",
      "risk": {
        "score": 0,
        "level": "低",
        "color": "#22c55e",
        "alerts": []
      },
      "lockups": [],
      "pledge": {
        "topPledgeRatio": 0,
        "topHolder": "",
        "totalPledge": 0
      },
      "goodwill": {
        "goodwill": 0,
        "netAssets": 1,
        "ratio": 0,
        "reportDate": "2026-03-31 00:00:00"
      },
      "changes": [],
      "checkedAt": "2026-06-09T15:51:53.476Z"
    },
    {
      "n": "立讯精密",
      "c": "002475",
      "m": 0,
      "eco": "",
      "tier": "",
      "risk": {
        "score": 0,
        "level": "低",
        "color": "#22c55e",
        "alerts": []
      },
      "lockups": [],
      "pledge": {
        "topPledgeRatio": 0,
        "topHolder": "",
        "totalPledge": 0
      },
      "goodwill": {
        "goodwill": 0,
        "netAssets": 1,
        "ratio": 0,
        "reportDate": "2026-03-31 00:00:00"
      },
      "changes": [],
      "checkedAt": "2026-06-09T15:51:53.977Z"
    },
    {
      "n": "歌尔股份",
      "c": "002241",
      "m": 0,
      "eco": "",
      "tier": "",
      "risk": {
        "score": 0,
        "level": "低",
        "color": "#22c55e",
        "alerts": []
      },
      "lockups": [],
      "pledge": {
        "topPledgeRatio": 0,
        "topHolder": "",
        "totalPledge": 0
      },
      "goodwill": {
        "goodwill": 0,
        "netAssets": 1,
        "ratio": 0,
        "reportDate": "2026-03-31 00:00:00"
      },
      "changes": [],
      "checkedAt": "2026-06-09T15:51:55.164Z"
    },
    {
      "n": "深南电路",
      "c": "002916",
      "m": 0,
      "eco": "",
      "tier": "",
      "risk": {
        "score": 0,
        "level": "低",
        "color": "#22c55e",
        "alerts": []
      },
      "lockups": [],
      "pledge": {
        "topPledgeRatio": 0,
        "topHolder": "",
        "totalPledge": 0
      },
      "goodwill": {
        "goodwill": 0,
        "netAssets": 1,
        "ratio": 0,
        "reportDate": "2026-03-31 00:00:00"
      },
      "changes": [],
      "checkedAt": "2026-06-09T15:51:57.372Z"
    },
    {
      "n": "通富微电",
      "c": "002156",
      "m": 0,
      "eco": "",
      "tier": "",
      "risk": {
        "score": 0,
        "level": "低",
        "color": "#22c55e",
        "alerts": []
      },
      "lockups": [],
      "pledge": {
        "topPledgeRatio": 0,
        "topHolder": "",
        "totalPledge": 0
      },
      "goodwill": {
        "goodwill": 0,
        "netAssets": 1,
        "ratio": 0,
        "reportDate": "2026-03-31 00:00:00"
      },
      "changes": [],
      "checkedAt": "2026-06-09T15:51:57.988Z"
    }
  ]
}